Octagon/__init__.py
Octagon-1.0.8.dist-info/LICENSE
Octagon-1.0.8.dist-info/METADATA
Octagon-1.0.8.dist-info/WHEEL
Octagon-1.0.8.dist-info/entry_points.txt
Octagon-1.0.8.dist-info/top_level.txt
Octagon-1.0.8.dist-info/RECORD
