Metadata-Version: 2.1
Name: Octagon
Version: 1.0.8
Summary: How can I find an octagon? How, Elmo? How?
Home-page: https://github.com/Cloud11665/octagon
Author: Cloud11665
Author-email: Cloud11665@gmail.com
License: gpl-3.0
Platform: UNKNOWN
Classifier: Programming Language :: Python :: 3.6
Classifier: Programming Language :: Python :: 3.7
Classifier: Programming Language :: Python :: 3.8
Classifier: Programming Language :: Python :: 3.9
Classifier: Operating System :: OS Independent
Requires-Python: >=3.6
Requires-Dist: click (==7.1.2)
Requires-Dist: numpy (==1.19.1)
Requires-Dist: opencv-python (==4.4.0.42)
